tglogging/__init__.py
tglogging/tglogger.py
tglogging_black-0.1.8.dist-info/LICENSE
tglogging_black-0.1.8.dist-info/METADATA
tglogging_black-0.1.8.dist-info/WHEEL
tglogging_black-0.1.8.dist-info/top_level.txt
tglogging_black-0.1.8.dist-info/RECORD
