Metadata-Version: 2.1
Name: tglogging-black
Version: 0.1.8
Summary: A python package to stream your app logs to a telegram chat in realtime.
Home-page: https://github.com/eyMarv/tglogging
Author: eyMarv
License: MIT
Project-URL: Tracker, https://github.com/eyMarv/tglogging/issues
Project-URL: Source, https://github.com/eyMarv/tglogging
Classifier: Programming Language :: Python :: 3
Classifier: License :: OSI Approved :: MIT License
Classifier: Operating System :: OS Independent
Requires-Python: >=3.8
License-File: LICENSE
Requires-Dist: aiohttp >=3.9.3
